<author lang="en">
	<documents>
		<document><![CDATA[Never related more in my life @zaynmalik https://t.co/jgsaTvVUSK]]></document>
		<document><![CDATA[@OfficialWith1D @KingsOfLeon who is she]]></document>
		<document><![CDATA[:)) #BRITVIDONEDIRECTION]]></document>
		<document><![CDATA[@OfficialWith1D #BRITVIDONEDIRECTION]]></document>
		<document><![CDATA[@moonliqhted what happened?]]></document>
		<document><![CDATA[@zaynmalik HAPPY BIRTHDAY ZAIN]]></document>
		<document><![CDATA[@OfficialWith1D what does he mean by put 1d aside?]]></document>
		<document><![CDATA[IT'S FINALLY 2017 PEOPLE https://t.co/SmSLbYkGcw]]></document>
		<document><![CDATA[@Harry_Styles FINALLY]]></document>
		<document><![CDATA[@JoshDevineDrums @BenDevine1994 how old is he]]></document>
		<document><![CDATA[@JoshDevineDrums @BenDevine1994 HAPPY NEW YEAR AND HAPPY BIRTHDAY]]></document>
		<document><![CDATA[Me rn #HAPPYNEWYEAR https://t.co/HB8sk5D5C1]]></document>
		<document><![CDATA[Still waiting for harry's tweet. It's still 2016]]></document>
		<document><![CDATA[@larryspureheart it's art]]></document>
		<document><![CDATA[@Harry_Styles @Louis_Tomlinson UGH UGH UGH]]></document>
		<document><![CDATA[@Louis_Tomlinson happy birthday sunshine hope you're happier than ever ik you mum is very proud of youðŸ’˜ #HappyBirthdayLouisTomlinson]]></document>
		<document><![CDATA[Yay he is finally 7 #HappyBirthdayLouisTomlinson]]></document>
		<document><![CDATA[@Louis_Tomlinson we thank you]]></document>
		<document><![CDATA[@Louis_Tomlinson we're so proud of you Lil son]]></document>
		<document><![CDATA[@Louis_Tomlinson you shouldn't thank us you deserve the whole thing]]></document>
		<document><![CDATA[@OfficialWith1D thank god he's there]]></document>
		<document><![CDATA[@larryspureheart welcome to the fam]]></document>
		<document><![CDATA[@zoifount @zaynmalik look at this zayyyyn]]></document>
		<document><![CDATA[@fakedeepharry lucky youu I live in Greece so...]]></document>
		<document><![CDATA[Anyone the link for 10? #skam link]]></document>
		<document><![CDATA[I NEED THE LINK FOR EP 9 SEASON 3 AND NOT GOOGLE DRIVE #skam link]]></document>
		<document><![CDATA[@nialls_hat @Hazzaynjm12 THIS IS SO GUUNY]]></document>
		<document><![CDATA[@LiamPayne IT'S BEEN 5 YEARS AND I'M STILL TRYING TO GERT ONE]]></document>
		<document><![CDATA[@LiamPayne ONCE AGAIN I DIDN'T GET AN ANSWER YAY]]></document>
		<document><![CDATA[@arianator_angie @LiamPayne that's life]]></document>
		<document><![CDATA[@LiamPayne @ayalouis7 I CAN'T HENDALL THIS]]></document>
		<document><![CDATA[@LiamPayne #askliam I'm supposed to be studying rn but who cares? Tbh not you]]></document>
		<document><![CDATA[@arianator_angie @LiamPayne YEAH I KNOWðŸ˜‚ðŸ˜‚]]></document>
		<document><![CDATA[@LiamPayne #askliam come here I wont tell cheryl]]></document>
		<document><![CDATA[@LiamPayne #askliam FOLLOW ME]]></document>
		<document><![CDATA[@LiamPayne #askliam I love your answers ðŸ˜‚ðŸ˜‚ðŸ˜‚ðŸ˜‚]]></document>
		<document><![CDATA[@LiamPayne #askliam I can see ya sitting there texting Louis for a sassy answer to the questions]]></document>
		<document><![CDATA[@LiamPayne #askliam how long is your...Christmas tree]]></document>
		<document><![CDATA[@LiamPayne #askliam it feels like talking to wall I love our relationship]]></document>
		<document><![CDATA[@LiamPayne #askliam are ya alive? *I'm waiting for a sassy answer*]]></document>
		<document><![CDATA[@LiamPayne #askliam your shoes that dayðŸ‘ŒðŸ‘ŒðŸ‘Œ https://t.co/Y2YxxTnSt9]]></document>
		<document><![CDATA[@LiamPayne #askliam SO SASSY AND FUNNY I'M DEAD AND CRYING]]></document>
		<document><![CDATA[@LiamPayne #askliam I want to go to the toilet but I'm afraid you'll make more tweets]]></document>
		<document><![CDATA[@LiamPayne @sadbutradrenee who's your man crush]]></document>
		<document><![CDATA[@LiamPayne @martinaarebecca SO SASSY I'M CRYING GOOD JOB LOUIS]]></document>
		<document><![CDATA[@LiamPayne #askliam what's the time there]]></document>
		<document><![CDATA[@LiamPayne #askliam I NEED TO WATCH SKAM BUT HERE I AM TALKING TO LITERALLY NO ONE]]></document>
		<document><![CDATA[@LiamPayne #askliam YOU'RE ALIVE I'M ALIVE]]></document>
		<document><![CDATA[@LiamPayne #askliam spooons who tops]]></document>
		<document><![CDATA[@LiamPayne #askliam I'm out of ideas]]></document>
		<document><![CDATA[@LiamPayne #askliam just to know I'm not rich and I can't buy 5 albums each year so get your asses and become a bad again]]></document>
		<document><![CDATA[@LiamPayne #askliam YOU'RE GONNA BE THE ONE THAT SAVES MEEEE]]></document>
		<document><![CDATA[@LiamPayne #askliam BECAUSE MAYBEEEEE]]></document>
		<document><![CDATA[@LiamPayne #askliam How long Is your....hair???]]></document>
		<document><![CDATA[@LiamPayne #askliam you're so funny I'm in tears]]></document>
		<document><![CDATA[@LiamPayne #askliam were you good at maths?]]></document>
		<document><![CDATA[@LiamPayne #askliam how long is your...hair?]]></document>
		<document><![CDATA[@LiamPayne #askliam WHAT AM I SUPPOSED TO ASK SO U CAN ANSWER ?]]></document>
		<document><![CDATA[@LiamPayne #askliam I miss the old days]]></document>
		<document><![CDATA[@LiamPayne #askliam I'm out of questions]]></document>
		<document><![CDATA[@LiamPayne #askliam greece loves you]]></document>
		<document><![CDATA[@LiamPayne #askliam what about Greece?]]></document>
		<document><![CDATA[@LiamPayne #askliam I love the gays]]></document>
		<document><![CDATA[@LiamPayne #askliam I command you to answer to me]]></document>
		<document><![CDATA[@LiamPayne #askliam with who are you rn?]]></document>
		<document><![CDATA[@LiamPayne #askliam I'm so excited even though you haven't answer to me]]></document>
		<document><![CDATA[@LiamPayne #askliam the Lil dog over there ðŸ˜]]></document>
		<document><![CDATA[@LiamPayne precious Lil boy #askliam]]></document>
		<document><![CDATA[@LiamPayne #askliam WE LOVE U HERE IN GREECE]]></document>
		<document><![CDATA[@LiamPayne #askliam I'm so happy seeing people's reaction to you answering to them]]></document>
		<document><![CDATA[@LiamPayne how was conjuring 2? #askliam]]></document>
		<document><![CDATA[@LiamPayne #askliam you're so precious]]></document>
		<document><![CDATA[@LiamPayne #askliam planning on visiting Greece?]]></document>
		<document><![CDATA[@LiamPayne #askliam the only person who has noticed me is @JoshDevineDrums THANK YOU JOSH]]></document>
		<document><![CDATA[@LiamPayne #askliam how is Louis doing?]]></document>
		<document><![CDATA[@LiamPayne #askliam I'm alive 
*not my screenshot* https://t.co/5aqn9soRui]]></document>
		<document><![CDATA[@LiamPayne #askliam so how is Cheryl doing ?]]></document>
		<document><![CDATA[@LiamPayne #askliam how are you]]></document>
		<document><![CDATA[How are u planning to spend your Christmas?  #askliam]]></document>
		<document><![CDATA[Should we expect an album any time soon ? #askliam]]></document>
		<document><![CDATA[When was the last time you talked to the boys? #askliam]]></document>
		<document><![CDATA[When was the last time you talked to zayn? #askliam]]></document>
		<document><![CDATA[@LiamPayne YOU'RE ALIVE]]></document>
		<document><![CDATA[@1DBreakUpdates @ElvisDuranShow what is he talking about]]></document>
		<document><![CDATA[Please let's just keep this trend going for a week at least  #ProudOfLouis]]></document>
		<document><![CDATA[@OT4WWUpdates @steveaoki what's his snapchat name?]]></document>
		<document><![CDATA[She is proud louis as we all are #ProudOfLouis https://t.co/VtJoaTYF6i]]></document>
		<document><![CDATA[@1DBreakUpdates I don't think so]]></document>
		<document><![CDATA[Can't even put my feelings into words this is just too much #ProudOfLouis]]></document>
		<document><![CDATA[@Louis_Tomlinson we're here for you as you've been here for us all these years]]></document>
		<document><![CDATA[@Louis_Tomlinson we're here for you]]></document>
		<document><![CDATA[I'm in tears the last thing we can do is show respect and affection to the family.]]></document>
		<document><![CDATA[If it's real I can't even say anything. My condolences to everyone in the family  #RIPJohannah]]></document>
		<document><![CDATA[@fizfizfiz really sorry love]]></document>
		<document><![CDATA[@Louis_Tomlinson stay strong Lil boy we're here]]></document>
		<document><![CDATA[I can't believe that]]></document>
		<document><![CDATA[@OfficialWith1D is it true?]]></document>
		<document><![CDATA[Idk if any of these is true but if it is I'm really sorry I can't imagine what the whole family is going through. My thoughts and prayers]]></document>
		<document><![CDATA[KALEO HOLIDAY VINYL GIFT - Win a Signed A/B Vinyl Record via @officialkaleo https://t.co/Yo99gwAXsy]]></document>
		<document><![CDATA[@Harry_StyleFolw I hadn't realise you were a fake account and I was like bitch what]]></document>
	</documents>
</author>